{"intents": [
  {"tag": "greetings",
  "patterns":["hello","hey","hi and hey","good day","Greetings","What's up ?","how is it going"],
  "responses": ["hello","Hey ! what can I do for you ?"]
  },
  {"tag": "goodbye",
  "patterns":["Cya","see you later !","hi and hey","Good Bye","I am leaving !","bye","cao"],
  "responses": ["Sad to see you go :(","Talk to you later","Good Bye!"]
  },
  {"tag": "name",
  "patterns":["what is your name ?","what should I call you ?","hi and hey","what's your name ?","who are you ?"],
  "responses": ["hello, myself Muffin🧁","You can call me muffin..."]
  },
  {"tag": "shop",
  "patterns":["Id like to buy something","What are your products ?","what do you recommend ?"],
  "responses": ["E-BAKERY has lots of products like that of muffins , cakes , pastries, cream rolls, slice cakes,"]
  },
  {"tag": "hour",
  "patterns":["when are you guys open ?","what are your hours ?","hours of operation"],
  "responses": ["24/7"]
  },
  {"tag": "delivery",
  "patterns":["Do you have delivery options ?","do you do home delivery ?","Is delivery there ?","Can u deliver to homes ?"],
  "responses": ["Yes ! we have delivery options ?"]
  },
  {"tag": "cod",
  "patterns":["is cash on delivery possible ?","Do you do Cash on delivery ?","Is cash on delivery possible ?","COD there ?"],
  "responses": ["Yes ! We have cash-on-delivery ! "]
  },
  {"tag": "online-payments",
  "patterns":["Do you take online payments ?","Is online payment there ?"],
  "responses": ["Yes ! We have payments system in online...."]
  }
]}